setup.py
pyunix/__init__.py
pyunix/shell.py
pyunix/testing.py
pyunixs.egg-info/PKG-INFO
pyunixs.egg-info/SOURCES.txt
pyunixs.egg-info/dependency_links.txt
pyunixs.egg-info/requires.txt
pyunixs.egg-info/top_level.txt