Metadata-Version: 2.1
Name: pyunixs
Version: 0.1
Summary: unix shell using python
Home-page: https://bitbucket.org/kishored27/pyunix/src/main/
Author: kishore
Author-email: kishoredurai7@gmail.com
License: UNKNOWN
Platform: UNKNOWN
